lacardlabs/__init__.py
lacardlabs-0.0.0a0.dist-info/METADATA
lacardlabs-0.0.0a0.dist-info/WHEEL
lacardlabs-0.0.0a0.dist-info/RECORD
