Metadata-Version: 2.4
Name: lacardlabs
Version: 0.0.0a0
Summary: Reserved placeholder for the LacardLabs project
Project-URL: Homepage, https://lacardlabs.com
Project-URL: Repository, https://github.com/LacardLabs/lacardlabs
Author: LacardLabs
License: MIT
Keywords: lacardlabs,placeholder
Classifier: Development Status :: 1 - Planning
Classifier: Intended Audience :: Developers
Classifier: License :: OSI Approved :: MIT License
Classifier: Programming Language :: Python :: 3
Requires-Python: >=3.10
